bingo-bongo-cat/__init__.py
bingo-bongo-cat/bingo_bongo_cat.py
bingo_bongo_cat/__init__.py
bingo_bongo_cat/bingo_bongo_cat.py
bingo_bongo_cat-0.0.8.dist-info/LICENSE
bingo_bongo_cat-0.0.8.dist-info/METADATA
bingo_bongo_cat-0.0.8.dist-info/WHEEL
bingo_bongo_cat-0.0.8.dist-info/top_level.txt
bingo_bongo_cat-0.0.8.dist-info/RECORD
