Metadata-Version: 2.1
Name: bingo-bongo-cat
Version: 0.0.8
Summary: Cat that prints messages.
Author: Kyle Levy
Author-email: 
Keywords: python,debugging,cat,funny
Classifier: Development Status :: 1 - Planning
Classifier: Intended Audience :: Developers
Classifier: Programming Language :: Python :: 3
Classifier: Operating System :: Unix
Classifier: Operating System :: MacOS :: MacOS X
Classifier: Operating System :: Microsoft :: Windows
License-File: LICENSE
